bisect_list/__init__.py
bisect_list/bisect.py
bisect_list/bisect_exception.py
bisect_list/functional.py
bisect_list/remove_unrelated.py
bisect_list-0.1.1.dist-info/WHEEL
bisect_list-0.1.1.dist-info/METADATA
bisect_list-0.1.1.dist-info/RECORD
