Metadata-Version: 2.1
Name: bisect-list
Version: 0.1.1
Summary: Find bad values in a list, logarithmically (FAST)!
Home-page: https://git.sr.ht/~munro/python-bisect-list
Author: Ryan Munro
Author-email: 500774+munro@users.noreply.github.com
Requires-Python: >=3.10,<4.0
Classifier: Programming Language :: Python :: 3
Classifier: Programming Language :: Python :: 3.10
Classifier: Programming Language :: Python :: 3.11
Project-URL: Repository, https://git.sr.ht/~munro/python-bisect-list
